LICENSE
README.rst
setup.py
django_postgres_queue.egg-info/PKG-INFO
django_postgres_queue.egg-info/SOURCES.txt
django_postgres_queue.egg-info/dependency_links.txt
django_postgres_queue.egg-info/requires.txt
django_postgres_queue.egg-info/top_level.txt
dpq/__init__.py
dpq/admin.py
dpq/apps.py
dpq/commands.py
dpq/decorators.py
dpq/models.py
dpq/queue.py
dpq/tests.py
dpq/migrations/0001_initial.py
dpq/migrations/0002_auto_20190419_2057.py
dpq/migrations/0003_alter_job_args.py
dpq/migrations/__init__.py
dpq_scheduler/__init__.py
dpq_scheduler/apps.py
dpq_scheduler/commands.py
dpq_scheduler/models.py
dpq_scheduler/schedules.py
dpq_scheduler/tests.py
dpq_scheduler/migrations/0001_initial.py
dpq_scheduler/migrations/__init__.py