Metadata-Version: 2.1
Name: django-postgres-queue
Version: 1.0.0
Summary: UNKNOWN
Home-page: https://github.com/gavinwahl/django-postgres-queue
Author: Gavin Wahl
Author-email: gavinwahl@gmail.com
License: BSD
Platform: UNKNOWN
License-File: LICENSE
